simpletimer/__init__.py
simpletimer/timer.py
simpletimer_kafka-0.1.9.dist-info/LICENSE
simpletimer_kafka-0.1.9.dist-info/WHEEL
simpletimer_kafka-0.1.9.dist-info/METADATA
simpletimer_kafka-0.1.9.dist-info/RECORD
