Metadata-Version: 2.1
Name: simpletimer-kafka
Version: 0.1.9
Summary: 
Author: Mathias Ho
Requires-Python: >=3.8,<4.0
Classifier: Programming Language :: Python :: 3
Classifier: Programming Language :: Python :: 3.8
Classifier: Programming Language :: Python :: 3.9
Classifier: Programming Language :: Python :: 3.10
Requires-Dist: confluent-kafka (>=1.9.2,<2.0.0)
Requires-Dist: kafka-python (>=2.0.2,<3.0.0)
